Metadata-Version: 2.4
Name: mcpcn-video-ai-subtitle-mcp
Version: 0.1.5
Summary: MCP server for AI-powered video subtitle generation and merging using Volcano Engine speech recognition
Author-email: Your Name <your.email@example.com>
License: MIT
Keywords: ai,ffmpeg,mcp,speech-recognition,srt,subtitle,video
Classifier: Development Status :: 4 - Beta
Classifier: Intended Audience :: Developers
Classifier: License :: OSI Approved :: MIT License
Classifier: Programming Language :: Python :: 3
Classifier: Programming Language :: Python :: 3.12
Classifier: Topic :: Multimedia :: Sound/Audio :: Speech
Classifier: Topic :: Multimedia :: Video
Classifier: Topic :: Software Development :: Libraries :: Python Modules
Requires-Python: >=3.12
Requires-Dist: ffmpeg-python>=0.2.0
Requires-Dist: mcp[cli]>=1.9.0
Requires-Dist: requests>=2.28.0
